cmem_plugin_currencies/__init__.py
cmem_plugin_currencies/eurofxref-hist.csv
cmem_plugin_currencies/eurofxref.py
cmem_plugin_currencies/exceptions.py
cmem_plugin_currencies/transform.py
cmem_plugin_currencies-0.10.0.dist-info/METADATA
cmem_plugin_currencies-0.10.0.dist-info/WHEEL
cmem_plugin_currencies-0.10.0.dist-info/licenses/LICENSE
cmem_plugin_currencies-0.10.0.dist-info/RECORD
